{
  "type": "minecraft:chest",
  "pools": [
    {
      "rolls": {
        "min": 0,
        "max": 1
      },
      "bonus_rolls": {
        "min": 0,
        "max": 1
      },
      "entries": [
        {
          "type": "minecraft:item",
          "name": "natures_spirit:shiitake_mushroom",
          "weight": 6,
          "functions": [
            {
              "count": {
                "min": 2,
                "max": 4
              },
              "function": "minecraft:set_count"
            }
          ]
        },
        {
          "type": "minecraft:item",
          "name": "natures_spirit:tiger_lily",
          "weight": 6,
          "functions": [
            {
              "count": {
                "min": 2,
                "max": 4
              },
              "function": "minecraft:set_count"
            }
          ]
        },
        {
          "type": "minecraft:item",
          "name": "natures_spirit:blue_iris",
          "weight": 6,
          "functions": [
            {
              "count": {
                "min": 2,
                "max": 4
              },
              "function": "minecraft:set_count"
            }
          ]
        },
        {
          "type": "minecraft:item",
          "name": "natures_spirit:black_iris",
          "weight": 6,
          "functions": [
            {
              "count": {
                "min": 2,
                "max": 4
              },
              "function": "minecraft:set_count"
            }
          ]
        },
        {
          "type": "minecraft:item",
          "name": "natures_spirit:red_heather",
          "weight": 6,
          "functions": [
            {
              "count": {
                "min": 2,
                "max": 4
              },
              "function": "minecraft:set_count"
            }
          ]
        },
        {
          "type": "minecraft:item",
          "name": "natures_spirit:white_heather",
          "weight": 6,
          "functions": [
            {
              "count": {
                "min": 2,
                "max": 4
              },
              "function": "minecraft:set_count"
            }
          ]
        },
        {
          "type": "minecraft:item",
          "name": "natures_spirit:purple_heather",
          "weight": 6,
          "functions": [
            {
              "count": {
                "min": 2,
                "max": 4
              },
              "function": "minecraft:set_count"
            }
          ]
        },
        {
          "type": "minecraft:item",
          "name": "natures_spirit:large_flaxen_fern",
          "weight": 6,
          "functions": [
            {
              "count": {
                "min": 2,
                "max": 4
              },
              "function": "minecraft:set_count"
            }
          ]
        },
        {
          "type": "minecraft:item",
          "name": "natures_spirit:large_lush_fern",
          "weight": 6,
          "functions": [
            {
              "count": {
                "min": 2,
                "max": 4
              },
              "function": "minecraft:set_count"
            }
          ]
        },
        {
          "type": "minecraft:item",
          "name": "natures_spirit:flaxen_fern",
          "weight": 6,
          "functions": [
            {
              "count": {
                "min": 2,
                "max": 4
              },
              "function": "minecraft:set_count"
            }
          ]
        },
        {
          "type": "minecraft:item",
          "name": "natures_spirit:lush_fern",
          "weight": 6,
          "functions": [
            {
              "count": {
                "min": 2,
                "max": 4
              },
              "function": "minecraft:set_count"
            }
          ]
        },
        {
          "type": "minecraft:item",
          "name": "natures_spirit:snapdragon",
          "weight": 6,
          "functions": [
            {
              "count": {
                "min": 2,
                "max": 4
              },
              "function": "minecraft:set_count"
            }
          ]
        }
      ]
    }
  ]
}